pySTAD-0.2.11.data/data/etc/jupyter/nbconfig/notebook.d/jupyter_stad.json
pySTAD-0.2.11.data/data/share/jupyter/labextensions/jupyter_stad/480.5f768159e8ba459021f9.js
pySTAD-0.2.11.data/data/share/jupyter/labextensions/jupyter_stad/480.5f768159e8ba459021f9.js.LICENSE.txt
pySTAD-0.2.11.data/data/share/jupyter/labextensions/jupyter_stad/568.90d8c79e4c3e52601126.js
pySTAD-0.2.11.data/data/share/jupyter/labextensions/jupyter_stad/568.90d8c79e4c3e52601126.js.LICENSE.txt
pySTAD-0.2.11.data/data/share/jupyter/labextensions/jupyter_stad/__init__.py
pySTAD-0.2.11.data/data/share/jupyter/labextensions/jupyter_stad/install.json
pySTAD-0.2.11.data/data/share/jupyter/labextensions/jupyter_stad/package.json
pySTAD-0.2.11.data/data/share/jupyter/labextensions/jupyter_stad/remoteEntry.09ad0fb12332fec69d43.js
pySTAD-0.2.11.data/data/share/jupyter/labextensions/jupyter_stad/style.js
pySTAD-0.2.11.data/data/share/jupyter/labextensions/jupyter_stad/third-party-licenses.json
pySTAD-0.2.11.data/data/share/jupyter/labextensions/jupyter_stad/labextension/__init__.py
pySTAD-0.2.11.data/data/share/jupyter/labextensions/jupyter_stad/labextension/package.json
pySTAD-0.2.11.data/data/share/jupyter/labextensions/jupyter_stad/labextension/static/480.5f768159e8ba459021f9.js
pySTAD-0.2.11.data/data/share/jupyter/labextensions/jupyter_stad/labextension/static/480.5f768159e8ba459021f9.js.LICENSE.txt
pySTAD-0.2.11.data/data/share/jupyter/labextensions/jupyter_stad/labextension/static/568.90d8c79e4c3e52601126.js
pySTAD-0.2.11.data/data/share/jupyter/labextensions/jupyter_stad/labextension/static/568.90d8c79e4c3e52601126.js.LICENSE.txt
pySTAD-0.2.11.data/data/share/jupyter/labextensions/jupyter_stad/labextension/static/remoteEntry.09ad0fb12332fec69d43.js
pySTAD-0.2.11.data/data/share/jupyter/labextensions/jupyter_stad/labextension/static/style.js
pySTAD-0.2.11.data/data/share/jupyter/labextensions/jupyter_stad/labextension/static/third-party-licenses.json
pySTAD-0.2.11.dist-info/LICENSE
pySTAD-0.2.11.dist-info/METADATA
pySTAD-0.2.11.dist-info/WHEEL
pySTAD-0.2.11.dist-info/entry_points.txt
pySTAD-0.2.11.dist-info/top_level.txt
pySTAD-0.2.11.dist-info/RECORD
