Metadata-Version: 2.1
Name: pySTAD
Version: 0.2.11
Summary: Dimensionality reduction through Simplified Topological Abstraction of Data
Home-page: https://gitlab.com/dsi_uhasselt/vda-lab/pystad2
Author: Jelmer Bot
Author-email: jelmer.bot@uhasselt.be
License: MIT
Project-URL: Code, https://gitlab.com/dsi_uhasselt/vda-lab/pystad2
Project-URL: Issue tracker, https://gitlab.com/dsi_uhasselt/vda-lab/pystad2/-/issues
Classifier: Development Status :: 4 - Beta
Classifier: Framework :: IPython
Classifier: License :: OSI Approved :: MIT License
Classifier: Intended Audience :: Education
Classifier: Intended Audience :: Science/Research
Classifier: Topic :: Scientific/Engineering
Classifier: Topic :: Scientific/Engineering :: Visualization
Classifier: Topic :: Multimedia :: Graphics
Classifier: Natural Language :: English
Classifier: Operating System :: OS Independent
Classifier: Programming Language :: Cython
Classifier: Programming Language :: Python
Classifier: Programming Language :: Python :: 3
Classifier: Programming Language :: Python :: 3.7
Classifier: Programming Language :: Python :: 3 :: Only
Classifier: Programming Language :: Python :: Implementation :: CPython
Requires-Python: >=3.7
License-File: LICENSE
Requires-Dist: numpy >=1.20.0
Requires-Dist: networkx >=3.0.0
Requires-Dist: scipy >=1.6.3
Requires-Dist: matplotlib >=3.4.2
Requires-Dist: pandas >=1.1.0
Requires-Dist: ipywidgets >=7.6.3
Requires-Dist: pywin32 >=1.0 ; platform_system == "Windows"
Provides-Extra: development
Requires-Dist: Cython >=0.29.20 ; extra == 'development'
Provides-Extra: testing
Requires-Dist: pytest ; extra == 'testing'
Requires-Dist: pytest-cov ; extra == 'testing'
